jac_nlp/VERSION
jac_nlp/__init__.py
jac_nlp/config.py
jac_nlp/action_configs/__init__.py
jac_nlp/action_configs/bi_enc_action_config.py
jac_nlp/action_configs/cl_summer_action_config.py
jac_nlp/action_configs/paraphraser_action_config.py
jac_nlp/action_configs/sbert_sim_action_config.py
jac_nlp/action_configs/sentiment_action_config.py
jac_nlp/action_configs/summarization_action_config.py
jac_nlp/action_configs/text_seg_action_config.py
jac_nlp/action_configs/tfm_ner_action_config.py
jac_nlp/action_configs/topic_ext_action_config.py
jac_nlp/action_configs/use_enc_action_config.py
jac_nlp/action_configs/use_qa_action_config.py
jac_nlp/bi_enc/__init__.py
jac_nlp/bi_enc/bi_enc.py
jac_nlp/bi_enc/poly_enc.py
jac_nlp/bi_enc/requirements.txt
jac_nlp/bi_enc/sent_enc.py
jac_nlp/bi_enc/tests/__init__.py
jac_nlp/bi_enc/tests/test_bi_enc.py
jac_nlp/bi_enc/tests/fixtures/__init__.py
jac_nlp/bi_enc/tests/fixtures/bi_enc.jac
jac_nlp/bi_enc/utils/__init__.py
jac_nlp/bi_enc/utils/evaluate.py
jac_nlp/bi_enc/utils/model_config.json
jac_nlp/bi_enc/utils/models.py
jac_nlp/bi_enc/utils/tokenizer.py
jac_nlp/bi_enc/utils/train.py
jac_nlp/bi_enc/utils/train_config.json
jac_nlp/cl_summer/__init__.py
jac_nlp/cl_summer/cl_summer.py
jac_nlp/cl_summer/requirements.txt
jac_nlp/cl_summer/tests/__init__.py
jac_nlp/cl_summer/tests/test_cl_summer.py
jac_nlp/cl_summer/tests/fixtures/__init__.py
jac_nlp/cl_summer/tests/fixtures/cl_summer.jac
jac_nlp/dolly/__init__.py
jac_nlp/dolly/dolly.py
jac_nlp/dolly/requirements.txt
jac_nlp/gpt2/__init__.py
jac_nlp/gpt2/gpt2.py
jac_nlp/gpt2/requirements.txt
jac_nlp/gpt2/train.py
jac_nlp/llm/__init__.py
jac_nlp/llm/dataset_builder.py
jac_nlp/llm/llm.py
jac_nlp/llm/requirements.txt
jac_nlp/paraphraser/__init__.py
jac_nlp/paraphraser/config.cfg
jac_nlp/paraphraser/paraphraser.py
jac_nlp/paraphraser/requirements.txt
jac_nlp/paraphraser/tests/__init__.py
jac_nlp/paraphraser/tests/test_paraphraser.py
jac_nlp/paraphraser/tests/fixtures/__init__.py
jac_nlp-1.4.2.6.dist-info/METADATA
jac_nlp-1.4.2.6.dist-info/WHEEL
jac_nlp-1.4.2.6.dist-info/top_level.txt
jac_nlp-1.4.2.6.dist-info/RECORD
