Metadata-Version: 2.1
Name: jac_nlp
Version: 1.4.2.6
Home-page: https://github.com/Jaseci-Labs/jaseci
Author: Jason Mars
Author-email: jason@jaseci.org
Requires-Dist: jaseci ==1.4.2.6
Requires-Dist: pytest <7.1,>=7.0.1
Requires-Dist: pytest-order <1.1,>=1.0.1
Provides-Extra: all
Requires-Dist: transformers >=4.25.1 ; extra == 'all'
Requires-Dist: beautifulsoup4 <4.13.0,>=4.12.2 ; extra == 'all'
Requires-Dist: torch <2.0.0,>=1.10.2 ; extra == 'all'
Requires-Dist: sentence-transformers <2.3,>=2.2.0 ; extra == 'all'
Requires-Dist: torch ==1.13.1 ; extra == 'all'
Requires-Dist: spacy ==3.3.0 ; extra == 'all'
Requires-Dist: transformers ==4.25.1 ; extra == 'all'
Requires-Dist: datasets ==2.8.0 ; extra == 'all'
Requires-Dist: evaluate <0.3,>=0.2.2 ; extra == 'all'
Requires-Dist: seqeval <1.3,>=1.2.2 ; extra == 'all'
Requires-Dist: tensorflow-hub <1.0.0,>=0.12.0 ; extra == 'all'
Requires-Dist: tensorflow-text <2.9.0,>=2.7.3 ; extra == 'all'
Requires-Dist: tensorflow <2.9.0,>=2.8.0 ; extra == 'all'
Requires-Dist: torch ; extra == 'all'
Requires-Dist: numpy >=1.23.0 ; extra == 'all'
Requires-Dist: scikit-learn >=1.2.0 ; extra == 'all'
Requires-Dist: pandas ==1.5.2 ; extra == 'all'
Requires-Dist: sentencepiece ==0.1.95 ; extra == 'all'
Requires-Dist: sentence-transformers ==2.2.2 ; extra == 'all'
Requires-Dist: scikit-learn >=0.24.2 ; extra == 'all'
Requires-Dist: emoji ==0.6.0 ; extra == 'all'
Requires-Dist: protobuf <3.21.0 ; extra == 'all'
Requires-Dist: transformers <5.0.0,>=4.25.1 ; extra == 'all'
Requires-Dist: numpy <2.0.0,>=1.23.5 ; extra == 'all'
Requires-Dist: accelerate <0.19.0,>=0.18.0 ; extra == 'all'
Requires-Dist: langchain <0.1.0,>=0.0.151 ; extra == 'all'
Requires-Dist: transformers ; extra == 'all'
Requires-Dist: datasets ; extra == 'all'
Requires-Dist: loralib ; extra == 'all'
Requires-Dist: sentencepiece ; extra == 'all'
Requires-Dist: peft ; extra == 'all'
Requires-Dist: bitsandbytes ; extra == 'all'
Requires-Dist: scipy ; extra == 'all'
Requires-Dist: Xformers ; extra == 'all'
Requires-Dist: sumy ==0.11.0 ; extra == 'all'
Provides-Extra: bi_enc
Requires-Dist: transformers ==4.25.1 ; extra == 'bi_enc'
Requires-Dist: torch ==1.13.1 ; extra == 'bi_enc'
Provides-Extra: cl_summer
Requires-Dist: sumy ==0.11.0 ; extra == 'cl_summer'
Provides-Extra: dolly
Requires-Dist: transformers <5.0.0,>=4.25.1 ; extra == 'dolly'
Requires-Dist: numpy <2.0.0,>=1.23.5 ; extra == 'dolly'
Requires-Dist: torch <2.0.0,>=1.10.2 ; extra == 'dolly'
Requires-Dist: accelerate <0.19.0,>=0.18.0 ; extra == 'dolly'
Requires-Dist: langchain <0.1.0,>=0.0.151 ; extra == 'dolly'
Provides-Extra: gpt2
Requires-Dist: transformers >=4.25.1 ; extra == 'gpt2'
Requires-Dist: torch <2.0.0,>=1.10.2 ; extra == 'gpt2'
Requires-Dist: scikit-learn >=0.24.2 ; extra == 'gpt2'
Provides-Extra: llm
Requires-Dist: transformers ; extra == 'llm'
Requires-Dist: datasets ; extra == 'llm'
Requires-Dist: loralib ; extra == 'llm'
Requires-Dist: sentencepiece ; extra == 'llm'
Requires-Dist: peft ; extra == 'llm'
Requires-Dist: bitsandbytes ; extra == 'llm'
Requires-Dist: scipy ; extra == 'llm'
Requires-Dist: Xformers ; extra == 'llm'
Provides-Extra: paraphraser
Requires-Dist: transformers >=4.25.1 ; extra == 'paraphraser'
Requires-Dist: sentencepiece ==0.1.95 ; extra == 'paraphraser'
Requires-Dist: torch ==1.13.1 ; extra == 'paraphraser'
Requires-Dist: protobuf <3.21.0 ; extra == 'paraphraser'
Provides-Extra: sbert_sim
Requires-Dist: sentence-transformers <2.3,>=2.2.0 ; extra == 'sbert_sim'
Requires-Dist: torch ==1.13.1 ; extra == 'sbert_sim'
Provides-Extra: sentiment
Requires-Dist: transformers ==4.25.1 ; extra == 'sentiment'
Requires-Dist: emoji ==0.6.0 ; extra == 'sentiment'
Provides-Extra: summarization
Requires-Dist: transformers >=4.25.1 ; extra == 'summarization'
Requires-Dist: beautifulsoup4 <4.13.0,>=4.12.2 ; extra == 'summarization'
Requires-Dist: torch <2.0.0,>=1.10.2 ; extra == 'summarization'
Provides-Extra: text_seg
Requires-Dist: spacy ==3.3.0 ; extra == 'text_seg'
Requires-Dist: transformers ==4.25.1 ; extra == 'text_seg'
Requires-Dist: torch ==1.13.1 ; extra == 'text_seg'
Provides-Extra: tfm_ner
Requires-Dist: transformers ==4.25.1 ; extra == 'tfm_ner'
Requires-Dist: torch ==1.13.1 ; extra == 'tfm_ner'
Requires-Dist: datasets ==2.8.0 ; extra == 'tfm_ner'
Requires-Dist: evaluate <0.3,>=0.2.2 ; extra == 'tfm_ner'
Requires-Dist: seqeval <1.3,>=1.2.2 ; extra == 'tfm_ner'
Provides-Extra: topic_ext
Requires-Dist: torch ; extra == 'topic_ext'
Requires-Dist: numpy >=1.23.0 ; extra == 'topic_ext'
Requires-Dist: scikit-learn >=1.2.0 ; extra == 'topic_ext'
Requires-Dist: pandas ==1.5.2 ; extra == 'topic_ext'
Requires-Dist: transformers ==4.25.1 ; extra == 'topic_ext'
Requires-Dist: sentencepiece ==0.1.95 ; extra == 'topic_ext'
Requires-Dist: sentence-transformers ==2.2.2 ; extra == 'topic_ext'
Provides-Extra: use_enc
Requires-Dist: tensorflow-hub <1.0.0,>=0.12.0 ; extra == 'use_enc'
Requires-Dist: tensorflow-text <2.9.0,>=2.7.3 ; extra == 'use_enc'
Requires-Dist: tensorflow <2.9.0,>=2.8.0 ; extra == 'use_enc'
Provides-Extra: use_qa
Requires-Dist: tensorflow-hub <1.0.0,>=0.12.0 ; extra == 'use_qa'
Requires-Dist: tensorflow-text <2.9.0,>=2.7.3 ; extra == 'use_qa'
Requires-Dist: tensorflow <2.9.0,>=2.8.0 ; extra == 'use_qa'
